volvocarsapi/__init__.py
volvocarsapi/api.py
volvocarsapi/auth.py
volvocarsapi/models.py
volvocarsapi/py.typed
volvocarsapi/scopes.py
volvocarsapi/util.py
volvocarsapi-0.4.3.dist-info/METADATA
volvocarsapi-0.4.3.dist-info/WHEEL
volvocarsapi-0.4.3.dist-info/licenses/LICENSE
volvocarsapi-0.4.3.dist-info/RECORD
