Metadata-Version: 2.4
Name: volvocarsapi
Version: 0.4.3
Summary: Python client for the Volvo Cars API.
Project-URL: Homepage, https://github.com/thomasddn/volvo-cars-api
Project-URL: Issues, https://github.com/thomasddn/volvo-cars-api/issues
Project-URL: Funding, https://ko-fi.com/N4N7UZ6KN
Author: thomasddn
License-Expression: GPL-3.0
License-File: LICENSE
Classifier: Operating System :: OS Independent
Classifier: Programming Language :: Python :: 3
Requires-Python: >=3.12
Requires-Dist: aiohttp>=3.11.16
Requires-Dist: yarl>=1.18.3
